{
  "_fv": 60,
  "_type": "recipe",
  "definition": {
    "recipeType": "Crafting",
    "recipeRetstackSize": 1,
    "group": "",
    "cookingBookCategory": "MISC",
    "xpReward": 0.0,
    "cookingTime": 200,
    "craftingBookCategory": "MISC",
    "recipeShapeless": true,
    "recipeSlots": [
      {
        "value": "Items.BOOK"
      },
      {
        "value": "Items.FEATHER"
      },
      {
        "value": ""
      },
      {
        "value": "CUSTOM:InkBottle"
      },
      {
        "value": ""
      },
      {
        "value": ""
      },
      {
        "value": ""
      },
      {
        "value": ""
      },
      {
        "value": ""
      }
    ],
    "recipeReturnStack": {
      "value": "Items.WRITABLE_BOOK"
    },
    "name": "book_and_quill_alt_recipe",
    "namespace": "mod"
  }
}