{
  "_fv": 60,
  "_type": "livingentity",
  "definition": {
    "mobName": "Fire Elemental",
    "mobLabel": "",
    "mobModelName": "Modelfire_elemental",
    "mobModelTexture": "fire_elemental.png",
    "transparentModelCondition": {
      "fixedValue": false
    },
    "isShakingCondition": {
      "fixedValue": false
    },
    "solidBoundingBox": {
      "fixedValue": false
    },
    "visualScale": {
      "fixedValue": 1.0
    },
    "boundingBoxScale": {
      "fixedValue": 1.0
    },
    "modelLayers": [
      {
        "model": "Default",
        "texture": "fire_elemental_emmissive.png",
        "glow": true
      }
    ],
    "modelWidth": 0.6,
    "modelHeight": 1.5999999999999999,
    "modelShadowSize": 0.0,
    "mountedYOffset": 0.0,
    "hasSpawnEgg": true,
    "spawnEggBaseColor": {
      "value": -6213352,
      "falpha": 0.0
    },
    "spawnEggDotColor": {
      "value": -1917878,
      "falpha": 0.0
    },
    "creativeTab": {
      "value": "MISC"
    },
    "isBoss": false,
    "bossBarColor": "PINK",
    "bossBarType": "PROGRESS",
    "equipmentMainHand": {
      "value": ""
    },
    "equipmentOffHand": {
      "value": ""
    },
    "equipmentHelmet": {
      "value": ""
    },
    "equipmentBody": {
      "value": ""
    },
    "equipmentLeggings": {
      "value": ""
    },
    "equipmentBoots": {
      "value": ""
    },
    "mobBehaviourType": "Mob",
    "mobCreatureType": "UNDEFINED",
    "attackStrength": 3,
    "attackKnockback": 0.0,
    "knockbackResistance": 0.0,
    "movementSpeed": 0.2,
    "stepHeight": 0.6,
    "armorBaseValue": 6.0,
    "trackingRange": 64,
    "followRange": 32,
    "health": 40,
    "xpAmount": 6,
    "waterMob": false,
    "breatheUnderwater": {
      "fixedValue": false
    },
    "pushedByFluids": {
      "fixedValue": true
    },
    "flyingMob": true,
    "guiBoundTo": "<NONE>",
    "inventorySize": 9,
    "inventoryStackSize": 64,
    "disableCollisions": false,
    "ridable": false,
    "canControlForward": false,
    "canControlStrafe": false,
    "immuneToFire": true,
    "immuneToArrows": false,
    "immuneToFallDamage": true,
    "immuneToCactus": false,
    "immuneToDrowning": false,
    "immuneToLightning": false,
    "immuneToPotions": false,
    "immuneToPlayer": false,
    "immuneToExplosion": false,
    "immuneToTrident": false,
    "immuneToAnvil": false,
    "immuneToWither": false,
    "immuneToDragonBreath": false,
    "mobDrop": {
      "value": ""
    },
    "livingSound": {
      "value": "block.fire.ambient"
    },
    "hurtSound": {
      "value": "item.firecharge.use"
    },
    "deathSound": {
      "value": "block.fire.extinguish"
    },
    "stepSound": {
      "value": "block.campfire.crackle"
    },
    "entityDataEntries": [],
    "whenMobDies": {
      "name": "FireElementalBurst"
    },
    "onMobTickUpdate": {
      "name": "FireElementalSmoke"
    },
    "onInitialSpawn": {
      "name": "ElementalSlowFallingAssign"
    },
    "hasAI": true,
    "aiBase": "(none)",
    "aixml": "<xml xmlns=\"https://developers.google.com/blockly/xml\"><block type=\"aitasks_container\" deletable=\"false\" x=\"40\" y=\"40\"><next><block type=\"attack_entity\"><field name=\"insight\">FALSE</field><field name=\"nearby\">FALSE</field><field name=\"entity\">EntityPlayer</field><field name=\"condition\">null,null</field><next><block type=\"attack_on_collide\"><field name=\"speed\">1.2</field><field name=\"longmemory\">TRUE</field><field name=\"condition\">null,null</field><next><block type=\"attack_action\"><field name=\"callhelp\">FALSE</field><field name=\"condition\">null,null</field><next><block type=\"wander\"><field name=\"speed\">1</field><field name=\"condition\">null,null</field><next><block type=\"watch_closest_entity\"><field name=\"entity\">EntityPlayer</field><field name=\"radius\">6</field><field name=\"condition\">null,null</field><next><block type=\"fly\"><field name=\"speed\">0.9</field><field name=\"condition\">ElementalFlyCondition,ElementalFlyCondition</field><next><block type=\"look_around\"><field name=\"condition\">null,null</field><next><block type=\"swim_in_water\"><field name=\"condition\">null,null</field></block></next></block></next></block></next></block></next></block></next></block></next></block></next></block></next></block></xml>",
    "breedable": false,
    "tameable": false,
    "breedTriggerItems": [],
    "ranged": false,
    "rangedAttackItem": {
      "value": ""
    },
    "rangedItemType": "FireballProjectileProjectile",
    "rangedAttackInterval": 80,
    "rangedAttackRadius": 12.0,
    "spawnThisMob": true,
    "doesDespawnWhenIdle": true,
    "spawningCondition": {
      "name": "FireElementalSpawnCondition"
    },
    "spawningProbability": 2,
    "mobSpawningType": "monster",
    "minNumberOfMobsPerGroup": 1,
    "maxNumberOfMobsPerGroup": 1,
    "restrictionBiomes": [
      {
        "value": "nether"
      },
      {
        "value": "basalt_deltas"
      }
    ],
    "spawnInDungeons": false
  }
}