{
  "_fv": 60,
  "_type": "structure",
  "definition": {
    "structure": "shrine_earth_fix",
    "projection": "rigid",
    "ignoredBlocks": [
      {
        "value": "Blocks.STRUCTURE_BLOCK"
      }
    ],
    "spacing": 25,
    "separation": 10,
    "restrictionBiomes": [
      {
        "value": "#minecraft:is_forest"
      }
    ],
    "surfaceDetectionType": "OCEAN_FLOOR",
    "terrainAdaptation": "none",
    "generationStep": "UNDERGROUND_STRUCTURES",
    "size": 1,
    "maxDistanceFromCenter": 64,
    "jigsawPools": []
  }
}